README.txt
setup.py
changes/changes.txt
changes/history.txt
django_vcexport.egg-info/PKG-INFO
django_vcexport.egg-info/SOURCES.txt
django_vcexport.egg-info/dependency_links.txt
django_vcexport.egg-info/entry_points.txt
django_vcexport.egg-info/not-zip-safe
django_vcexport.egg-info/requires.txt
django_vcexport.egg-info/top_level.txt
vcexport/__init__.py
vcexport/models.py
vcexport/sven_stuff.py