Metadata-Version: 1.0
Name: django-vcexport
Version: 0.6
Summary: a flexible library for exporting serialized django model instances to a version-controlled repository automatically or manually
Home-page: UNKNOWN
Author: Ethan Jucovy
Author-email: ejucovy@gmail.com
License: GPL
Platform: UNKNOWN
Classifier: Development Status :: 3 - Alpha
Classifier: Environment :: Web Environment
Classifier: Intended Audience :: Developers
Classifier: Programming Language :: Python
Classifier: Framework :: Django
